disdat_step_function/__init__.py
disdat_step_function/cache_lambda.py
disdat_step_function/caching_wrapper.py
disdat_step_function/lambda_for_user.py
disdat_step_function/version.py
disdat_step_function-0.1.dev15.dist-info/LICENSE
disdat_step_function-0.1.dev15.dist-info/METADATA
disdat_step_function-0.1.dev15.dist-info/WHEEL
disdat_step_function-0.1.dev15.dist-info/top_level.txt
disdat_step_function-0.1.dev15.dist-info/RECORD
